{"run_number": "1719922109445413", "step_name": "load_transformed_data", "task_id": "5", "attempt_id": 0, "name": "_current_step", "content_type": "gzip+pickle-v2", "type": "metaflow.artifact", "sha": "866a58d2199c2887322e178303906340ca9b9c64", "ds_type": "local", "location": ":root:/Users/gaurav/Developer/ETL pipeline/.metaflow", "flow_id": "ETLFlow", "user_name": "gaurav", "tags": [], "system_tags": ["python_version:3.9.6", "user:gaurav", "runtime:dev", "metaflow_version:2.12.6"], "ts_epoch": 1719922120324}